<?xml version="1.0" encoding="UTF-8"?><record_update table="m2m_sys_suggestion_reader_sys_suggestion_reader_group">
    <m2m_sys_suggestion_reader_sys_suggestion_reader_group action="INSERT_OR_UPDATE">
        <order>200</order>
        <reader_requested_fields/>
        <reader_searchable_fields/>
        <sys_class_name>m2m_sys_suggestion_reader_sys_suggestion_reader_group</sys_class_name>
        <sys_created_by>max</sys_created_by>
        <sys_created_on>2023-07-05 17:47:59</sys_created_on>
        <sys_id>69d298a67bbfad90f0b47470347623a9</sys_id>
        <sys_mod_count>0</sys_mod_count>
        <sys_name/>
        <sys_package display_value="Value Stream Identification" source="x_492190_value_s_0">450e7ed62fb7ad900051309cf699b639</sys_package>
        <sys_policy/>
        <sys_scope display_value="Value Stream Identification">450e7ed62fb7ad900051309cf699b639</sys_scope>
        <sys_suggestion_reader_group_id display_value="User History Reader Group for Starter Workspace - Workspace Search">e1d298a67fbfad9085624594b64b619f</sys_suggestion_reader_group_id>
        <sys_suggestion_reader_id display_value="User History and Click Reader">f8495b9077210110be280d892c5a9986</sys_suggestion_reader_id>
        <sys_update_name>m2m_sys_suggestion_reader_sys_suggestion_reader_group_69d298a67bbfad90f0b47470347623a9</sys_update_name>
        <sys_updated_by>max</sys_updated_by>
        <sys_updated_on>2023-07-05 17:47:59</sys_updated_on>
    </m2m_sys_suggestion_reader_sys_suggestion_reader_group>
</record_update>
